rozha/.DS_Store
rozha/__init__.py
rozha/analyze.py
rozha/process.py
rozha/visualize.py
rozha-1.0.0.dist-info/METADATA
rozha-1.0.0.dist-info/WHEEL
rozha-1.0.0.dist-info/licenses/LICENSE
rozha-1.0.0.dist-info/RECORD
