Metadata-Version: 2.1
Name: rozha
Version: 1.0.0
Summary: A multifaceted tool to simplify NLP.
Project-URL: Homepage, https://github.com/ian-nai/rozha
Project-URL: Bug Tracker, https://github.com/ian-nai/rozha/issues
Author-email: Ian Goodale <ian.goodale@austin.utexas.edu>
License: GNU GENERAL PUBLIC LICENSE
License-File: LICENSE
Classifier: License :: OSI Approved :: GNU General Public License v3 (GPLv3)
Classifier: Operating System :: OS Independent
Classifier: Programming Language :: Python :: 3
Requires-Python: >=3.7
Requires-Dist: matplotlib==3.5.2
Requires-Dist: nltk==3.6.5
Requires-Dist: spacy==3.4.2
Requires-Dist: stanza==1.4.2
Requires-Dist: textblob==0.17.1
Requires-Dist: wordcloud==1.8.2.2
